edera/__init__.py
edera/condition.py
edera/consumer.py
edera/disjointset.py
edera/exceptions.py
edera/flag.py
edera/graph.py
edera/heap.py
edera/invoker.py
edera/linearizer.py
edera/locker.py
edera/nameable.py
edera/parameterizable.py
edera/partitioner.py
edera/qualifier.py
edera/qualifiers.py
edera/queue.py
edera/requisite.py
edera/requisites.py
edera/routine.py
edera/storage.py
edera/task.py
edera/worker.py
edera/consumers/__init__.py
edera/consumers/basic.py
edera/consumers/interprocess.py
edera/daemon/__init__.py
edera/daemon/autotester.py
edera/daemon/daemon.py
edera/daemon/modules.py
edera/daemon/schedule.py
edera/flags/__init__.py
edera/flags/interprocess.py
edera/flags/interthread.py
edera/helpers/__init__.py
edera/helpers/beanbag.py
edera/helpers/box.py
edera/helpers/boxes.py
edera/helpers/current_exception.py
edera/helpers/factory.py
edera/helpers/lazy.py
edera/helpers/phony.py
edera/helpers/proxy.py
edera/helpers/sasha.py
edera/helpers/serializable.py
edera/helpers/utilities.py
edera/invokers/__init__.py
edera/invokers/masterslave.py
edera/invokers/multiprocess.py
edera/invokers/multithreaded.py
edera/invokers/persistent.py
edera/linearizers/__init__.py
edera/linearizers/dfs.py
edera/lockers/__init__.py
edera/lockers/cascade.py
edera/lockers/directory.py
edera/lockers/process.py
edera/lockers/zookeeper.py
edera/managers/__init__.py
edera/managers/cascade.py
edera/managers/mongo.py
edera/managers/zookeeper.py
edera/monitoring/__init__.py
edera/monitoring/agent.py
edera/monitoring/snapshot.py
edera/monitoring/ui.py
edera/monitoring/watcher.py
edera/partitioners/__init__.py
edera/partitioners/greedy.py
edera/resources/monitoring/ui/static/favicon.ico
edera/resources/monitoring/ui/static/theme.css
edera/resources/monitoring/ui/templates/index.html
edera/resources/monitoring/ui/templates/page.html
edera/resources/monitoring/ui/templates/report.html
edera/resources/monitoring/ui/templates/void.html
edera/resources/monitoring/ui/templates/macros/task_state.html
edera-0.12.1.dist-info/LICENSE
edera-0.12.1.dist-info/METADATA
edera-0.12.1.dist-info/WHEEL
edera-0.12.1.dist-info/top_level.txt
edera-0.12.1.dist-info/RECORD
